tbcalc/__init__.py
tbcalc/analyser.py
tbcalc/johann_error.py
tbcalc/strip_bent.py
tbcalc/tensor_transform.py
tbcalc/transverse_deformation.py
tbcalc-1.0.dist-info/LICENSE
tbcalc-1.0.dist-info/METADATA
tbcalc-1.0.dist-info/WHEEL
tbcalc-1.0.dist-info/top_level.txt
tbcalc-1.0.dist-info/RECORD
